py_range_parse/__init__.py
py_range_parse-1.0.6.dist-info/licenses/LICENSE
tests/__init__.py
tests/comparison_test.py
tests/contains_test.py
tests/parse_test.py
tests/str_test.py
py_range_parse-1.0.6.dist-info/METADATA
py_range_parse-1.0.6.dist-info/WHEEL
py_range_parse-1.0.6.dist-info/top_level.txt
py_range_parse-1.0.6.dist-info/RECORD
