Metadata-Version: 2.4
Name: py_range_parse
Version: 1.0.6
Summary: Parses commonly used range notations to python objects
Home-page: https://github.com/markusressel/py-range-parse
Author: Markus Ressel
Author-email: mail@markusressel.de
License: MIT
Classifier: License :: OSI Approved :: MIT License
Classifier: Programming Language :: Python :: 3
Classifier: Programming Language :: Python :: 3.10
Classifier: Programming Language :: Python :: 3.11
Classifier: Programming Language :: Python :: 3.12
Classifier: Programming Language :: Python :: 3.13
License-File: LICENSE
Dynamic: author
Dynamic: author-email
Dynamic: classifier
Dynamic: description
Dynamic: description-content-type
Dynamic: home-page
Dynamic: license
Dynamic: license-file
Dynamic: summary
